{
    "Version": "2012-10-17",
    "Statement": [
        {
            "Sid": "VisualEditor0",
            "Effect": "Allow",
            "Action": [
                "logs:DescribeExportTasks",
                "logs:DeleteResourcePolicy",
                "logs:PutResourcePolicy",
                "logs:PutDestinationPolicy",
                "logs:CancelExportTask",
                "logs:TestMetricFilter",
                "logs:DeleteDestination",
                "logs:PutDestination",
                "logs:CreateLogGroup",
                "logs:DescribeResourcePolicies",
                "logs:DescribeDestinations"
            ],
            "Resource": "*"
        },
        {
            "Sid": "VisualEditor1",
            "Effect": "Allow",
            "Action": "logs:*",
            "Resource": "arn:aws:logs:REGION_HERE:ACCOUNT_NUMBER_HERE:log-group:COMPONENT_NAME_HERE*"
        }
    ]
}